LICENSE.txt
MANIFEST.in
README.rst
readme.rst
requirements.txt
setup.py
ssan/__init__.py
ssan/s3client.py
ssan/zzz_manual_install.py
ssan.egg-info/PKG-INFO
ssan.egg-info/SOURCES.txt
ssan.egg-info/dependency_links.txt
ssan.egg-info/requires.txt
ssan.egg-info/top_level.txt
ssan/__pycache__/__init__.cpython-33.pyc